makefile_help/__init__.py
makefile_help/__main__.py
makefile_help-0.1.1.dist-info/entry_points.txt
makefile_help-0.1.1.dist-info/LICENSE
makefile_help-0.1.1.dist-info/WHEEL
makefile_help-0.1.1.dist-info/METADATA
makefile_help-0.1.1.dist-info/RECORD
