Metadata-Version: 2.1
Name: makefile-help
Version: 0.1.1
Summary: Autogenerates pretty Makefile help
Home-page: https://github.com/simonwardjones/makefile-help
License: MIT
Author: simonwardjones
Author-email: simonwardjones@yahoo.co.uk
Requires-Python: >=3.7,<4.0
Classifier: Environment :: Console
Classifier: License :: OSI Approved :: MIT License
Classifier: Programming Language :: Python :: 3
Classifier: Programming Language :: Python :: 3.7
Classifier: Programming Language :: Python :: 3.8
Classifier: Programming Language :: Python :: 3.9
Classifier: Topic :: Software Development :: Build Tools
Classifier: Topic :: Terminals
